odoo/addons/edi_voxel_sale_order_import_oca/README.rst
odoo/addons/edi_voxel_sale_order_import_oca/__init__.py
odoo/addons/edi_voxel_sale_order_import_oca/__manifest__.py
odoo/addons/edi_voxel_sale_order_import_oca/data/ir_cron_data.xml
odoo/addons/edi_voxel_sale_order_import_oca/i18n/edi_voxel_sale_order_import_oca.pot
odoo/addons/edi_voxel_sale_order_import_oca/i18n/es.po
odoo/addons/edi_voxel_sale_order_import_oca/i18n/it.po
odoo/addons/edi_voxel_sale_order_import_oca/models/__init__.py
odoo/addons/edi_voxel_sale_order_import_oca/models/res_company.py
odoo/addons/edi_voxel_sale_order_import_oca/models/res_config_settings.py
odoo/addons/edi_voxel_sale_order_import_oca/models/sale_order.py
odoo/addons/edi_voxel_sale_order_import_oca/readme/CONFIGURE.md
odoo/addons/edi_voxel_sale_order_import_oca/readme/CONTRIBUTORS.md
odoo/addons/edi_voxel_sale_order_import_oca/readme/DESCRIPTION.md
odoo/addons/edi_voxel_sale_order_import_oca/readme/USAGE.md
odoo/addons/edi_voxel_sale_order_import_oca/security/ir.model.access.csv
odoo/addons/edi_voxel_sale_order_import_oca/security/voxel_sale_order_security.xml
odoo/addons/edi_voxel_sale_order_import_oca/static/description/icon.png
odoo/addons/edi_voxel_sale_order_import_oca/static/description/index.html
odoo/addons/edi_voxel_sale_order_import_oca/tests/__init__.py
odoo/addons/edi_voxel_sale_order_import_oca/tests/test_voxel_sale_order_import.py
odoo/addons/edi_voxel_sale_order_import_oca/tests/voxel_xml/Pedido_20190619_145750_0611125750634.xml
odoo/addons/edi_voxel_sale_order_import_oca/views/res_company_views.xml
odoo/addons/edi_voxel_sale_order_import_oca/views/res_config_settings_views.xml
odoo/addons/edi_voxel_sale_order_import_oca/views/sale_order_views.xml
odoo_addon_edi_voxel_sale_order_import_oca-18.0.1.0.1.dist-info/METADATA
odoo_addon_edi_voxel_sale_order_import_oca-18.0.1.0.1.dist-info/WHEEL
odoo_addon_edi_voxel_sale_order_import_oca-18.0.1.0.1.dist-info/top_level.txt
odoo_addon_edi_voxel_sale_order_import_oca-18.0.1.0.1.dist-info/RECORD
