Metadata-Version: 2.1
Name: odoo-addon-edi_voxel_sale_order_import_oca
Version: 18.0.1.0.1
Requires-Python: >=3.10
Requires-Dist: odoo-addon-edi_voxel_oca==18.0.*
Requires-Dist: odoo-addon-onchange_helper==18.0.*
Requires-Dist: odoo==18.0.*
Summary: Import sale order from Voxel.
Home-page: https://github.com/OCA/edi-voxel
License: AGPL-3
Author: Tecnativa, Odoo Community Association (OCA)
Author-email: support@odoo-community.org
Classifier: Programming Language :: Python
Classifier: Framework :: Odoo
Classifier: Framework :: Odoo :: 18.0
Classifier: License :: OSI Approved :: GNU Affero General Public License v3
